LICENSE.txt
MANIFEST.in
README.md
README.txt
setup.py
TimeDiff.egg-info/PKG-INFO
TimeDiff.egg-info/SOURCES.txt
TimeDiff.egg-info/dependency_links.txt
TimeDiff.egg-info/top_level.txt
timediff/__init__.py
timediff/cli_output.py
timediff/conf_reader.py
timediff/log_parser.py
timediff/timediff.json
timediff/doc/cli_output.m.html
timediff/doc/conf_reader.m.html
timediff/doc/log_parser.m.html