Metadata-Version: 1.1
Name: TimeDiff
Version: 0.9.38
Summary: Program for login and plotting time-differences in log-files.
Home-page: https://github.com/nomelif/time-diff
Author: Théo Friberg
Author-email: theo.friberg@gmail.com
License: The MIT License (MIT)
